print_queue_api_client/__init__.py
print_queue_api_client/database_api.py
print_queue_api_client/tables/base_table.py
print_queue_api_client/tables/job_table.py
print_queue_api_client/tables/printer_table.py
print_queue_api_client/tables/user_table.py
print_queue_api_client-0.0.12.dist-info/LICENSE
print_queue_api_client-0.0.12.dist-info/METADATA
print_queue_api_client-0.0.12.dist-info/WHEEL
print_queue_api_client-0.0.12.dist-info/top_level.txt
print_queue_api_client-0.0.12.dist-info/RECORD
